docker_git_build
