Metadata-Version: 1.1
Name: dgbuild
Version: 0.1.1
Summary: Build Docker containers based on git tags
Home-page: https://github.com/jcderr/docker-git-build
Author: Jeremy Derr
Author-email: jeremy@derr.me
License: BSD
Platform: any
Classifier: Development Status :: 4 - Beta
Classifier: Environment :: Console
Classifier: Intended Audience :: Developers
Classifier: Operating System :: POSIX
Classifier: Operating System :: MacOS
Classifier: Operating System :: Unix
Classifier: Programming Language :: Python
Classifier: Programming Language :: Python :: 2
Classifier: Programming Language :: Python :: 3
